MANIFEST.in
README.rst
README.txt
requirements.txt
setup.py
test_requirements.txt
version.txt
cloudshell/__init__.py
cloudshell/firewall/__init__.py
cloudshell/firewall/firewall_resource_driver_interface.py
cloudshell_firewall.egg-info/PKG-INFO
cloudshell_firewall.egg-info/SOURCES.txt
cloudshell_firewall.egg-info/dependency_links.txt
cloudshell_firewall.egg-info/top_level.txt