Metadata-Version: 1.0
Name: cloudshell-firewall
Version: 3.0.3
Summary: QualiSystems Python package
Home-page: https://github.com/QualiSystems/cloudshell-firewall
Author: QualiSystems
Author-email: info@qualisystems.com
License: UNKNOWN
Platform: UNKNOWN
